siiha_sdk/__init__.py
siiha_sdk/auth.py
siiha_sdk/calendar.py
siiha_sdk/config.py
siiha_sdk/nlp.py
siiha_sdk/utils.py
siiha_sdk-0.1.9.dist-info/licenses/LICENSE
siiha_sdk-0.1.9.dist-info/METADATA
siiha_sdk-0.1.9.dist-info/WHEEL
siiha_sdk-0.1.9.dist-info/top_level.txt
siiha_sdk-0.1.9.dist-info/RECORD
