Metadata-Version: 2.4
Name: siiha-sdk
Version: 0.1.9
Summary: SIIHA SDK — Natural language → Google Calendar create-event with dedupe
Author: Debby Yeh
License: MIT
Project-URL: Homepage, https://github.com/HUEI-JYUN-DEBBY-YEH/siiha-gemini-multiagent-ver2.git
Project-URL: Source, https://github.com/HUEI-JYUN-DEBBY-YEH/siiha-gemini-multiagent-ver2.git
Requires-Python: >=3.9
License-File: LICENSE
Requires-Dist: google-api-python-client>=2.132.0
Requires-Dist: google-auth-oauthlib>=1.2.0
Requires-Dist: python-dateutil>=2.9.0
Requires-Dist: pytz>=2024.1
Provides-Extra: dev
Requires-Dist: build>=1.2.2; extra == "dev"
Requires-Dist: twine>=5.0.0; extra == "dev"
Requires-Dist: pytest>=8.0.0; extra == "dev"
Dynamic: license-file
